hwp5/COPYING
hwp5/README
hwp5/VERSION.txt
hwp5/__init__.py
hwp5/binspec.py
hwp5/bintype.py
hwp5/charsets.py
hwp5/compressed.py
hwp5/dataio.py
hwp5/distdoc.py
hwp5/errors.py
hwp5/filestructure.py
hwp5/hwp5html.py
hwp5/hwp5odt.py
hwp5/hwp5txt.py
hwp5/hwp5view.py
hwp5/importhelper.py
hwp5/msoleprops.py
hwp5/recordstream.py
hwp5/summaryinfo.py
hwp5/tagids.py
hwp5/treeop.py
hwp5/utils.py
hwp5/xmldump_flat.py
hwp5/xmlformat.py
hwp5/xmlmodel.py
hwp5/zlib_raw_codec.py
hwp5/binmodel/__init__.py
hwp5/binmodel/_shared.py
hwp5/binmodel/controlchar.py
hwp5/binmodel/tagid16_document_properties.py
hwp5/binmodel/tagid17_id_mappings.py
hwp5/binmodel/tagid18_bin_data.py
hwp5/binmodel/tagid19_face_name.py
hwp5/binmodel/tagid20_border_fill.py
hwp5/binmodel/tagid21_char_shape.py
hwp5/binmodel/tagid22_tab_def.py
hwp5/binmodel/tagid23_numbering.py
hwp5/binmodel/tagid24_bullet.py
hwp5/binmodel/tagid25_para_shape.py
hwp5/binmodel/tagid26_style.py
hwp5/binmodel/tagid27_doc_data.py
hwp5/binmodel/tagid28_distribute_doc_data.py
hwp5/binmodel/tagid30_compatible_document.py
hwp5/binmodel/tagid31_layout_compatibility.py
hwp5/binmodel/tagid32_unknown.py
hwp5/binmodel/tagid50_para_header.py
hwp5/binmodel/tagid51_para_text.py
hwp5/binmodel/tagid52_para_char_shape.py
hwp5/binmodel/tagid53_para_line_seg.py
hwp5/binmodel/tagid54_para_range_tag.py
hwp5/binmodel/tagid55_ctrl_header.py
hwp5/binmodel/tagid56_list_header.py
hwp5/binmodel/tagid57_page_def.py
hwp5/binmodel/tagid58_footnote_shape.py
hwp5/binmodel/tagid59_page_border_fill.py
hwp5/binmodel/tagid60_shape_component.py
hwp5/binmodel/tagid61_table.py
hwp5/binmodel/tagid62_shape_component_line.py
hwp5/binmodel/tagid63_shape_component_rectangle.py
hwp5/binmodel/tagid64_shape_component_ellipse.py
hwp5/binmodel/tagid65_shape_component_arc.py
hwp5/binmodel/tagid66_shape_component_polygon.py
hwp5/binmodel/tagid67_shape_component_curve.py
hwp5/binmodel/tagid68_shape_component_ole.py
hwp5/binmodel/tagid69_shape_component_picture.py
devhwp-1.0.0.2.dist-info/COPYING
devhwp-1.0.0.2.dist-info/LICENSE
devhwp-1.0.0.2.dist-info/METADATA
devhwp-1.0.0.2.dist-info/WHEEL
devhwp-1.0.0.2.dist-info/entry_points.txt
devhwp-1.0.0.2.dist-info/top_level.txt
devhwp-1.0.0.2.dist-info/RECORD
